cms/__init__.py
cms-0.0.2.dist-info/METADATA
cms-0.0.2.dist-info/RECORD
cms-0.0.2.dist-info/WHEEL
cms-0.0.2.dist-info/top_level.txt
